setup.cfg
setup.py
netra/__init__.py
netra/base.py
netra/cli.py
netra/regression.py
netra/rnn.py
netra/utils.py
netra.egg-info/PKG-INFO
netra.egg-info/SOURCES.txt
netra.egg-info/dependency_links.txt
netra.egg-info/entry_points.txt
netra.egg-info/not-zip-safe
netra.egg-info/requires.txt
netra.egg-info/top_level.txt